ovsdbapp/CHANGES
ovsdbapp/__init__.py
ovsdbapp/api.py
ovsdbapp/constants.py
ovsdbapp/event.py
ovsdbapp/exceptions.py
ovsdbapp/utils.py
ovsdbapp/venv.py
ovsdbapp/backend/__init__.py
ovsdbapp/backend/ovs_idl/__init__.py
ovsdbapp/backend/ovs_idl/command.py
ovsdbapp/backend/ovs_idl/connection.py
ovsdbapp/backend/ovs_idl/event.py
ovsdbapp/backend/ovs_idl/fixtures.py
ovsdbapp/backend/ovs_idl/idlutils.py
ovsdbapp/backend/ovs_idl/rowview.py
ovsdbapp/backend/ovs_idl/transaction.py
ovsdbapp/backend/ovs_idl/vlog.py
ovsdbapp/backend/ovs_idl/common/__init__.py
ovsdbapp/backend/ovs_idl/common/base_connection_utils.py
ovsdbapp/backend/ovs_idl/linux/__init__.py
ovsdbapp/backend/ovs_idl/linux/connection_utils.py
ovsdbapp/backend/ovs_idl/windows/__init__.py
ovsdbapp/backend/ovs_idl/windows/connection_utils.py
ovsdbapp/backend/ovs_idl/windows/utils.py
ovsdbapp/schema/__init__.py
ovsdbapp/schema/hardware_vtep/__init__.py
ovsdbapp/schema/hardware_vtep/api.py
ovsdbapp/schema/hardware_vtep/commands.py
ovsdbapp/schema/hardware_vtep/impl_idl.py
ovsdbapp/schema/open_vswitch/__init__.py
ovsdbapp/schema/open_vswitch/api.py
ovsdbapp/schema/open_vswitch/commands.py
ovsdbapp/schema/open_vswitch/helpers.py
ovsdbapp/schema/open_vswitch/impl_idl.py
ovsdbapp/schema/ovn_ic_northbound/__init__.py
ovsdbapp/schema/ovn_ic_northbound/api.py
ovsdbapp/schema/ovn_ic_northbound/commands.py
ovsdbapp/schema/ovn_ic_northbound/impl_idl.py
ovsdbapp/schema/ovn_northbound/__init__.py
ovsdbapp/schema/ovn_northbound/api.py
ovsdbapp/schema/ovn_northbound/commands.py
ovsdbapp/schema/ovn_northbound/impl_idl.py
ovsdbapp/schema/ovn_southbound/__init__.py
ovsdbapp/schema/ovn_southbound/api.py
ovsdbapp/schema/ovn_southbound/commands.py
ovsdbapp/schema/ovn_southbound/impl_idl.py
ovsdbapp/tests/__init__.py
ovsdbapp/tests/base.py
ovsdbapp/tests/utils.py
ovsdbapp/tests/functional/__init__.py
ovsdbapp/tests/functional/base.py
ovsdbapp/tests/functional/backend/__init__.py
ovsdbapp/tests/functional/backend/ovs_idl/__init__.py
ovsdbapp-2.15.0.dist-info/licenses/AUTHORS
ovsdbapp-2.15.0.dist-info/licenses/LICENSE
ovsdbapp-2.15.0.dist-info/METADATA
ovsdbapp-2.15.0.dist-info/WHEEL
ovsdbapp-2.15.0.dist-info/pbr.json
ovsdbapp-2.15.0.dist-info/top_level.txt
ovsdbapp-2.15.0.dist-info/RECORD
